{
	"animations": [
		{
			"loop": false,
			"offsets": [
				0,
				0
			],
			"anim": "idle",
			"fps": 24,
			"name": "Ace Idle",
			"indices": []
		},
		{
			"loop": false,
			"offsets": [
				-1,
				2
			],
			"anim": "intro",
			"fps": 24,
			"name": "Ace Intro",
			"indices": []
		},
		{
			"loop": false,
			"offsets": [
				83,
				-86
			],
			"anim": "singDOWN",
			"fps": 24,
			"name": "Ace Down Note",
			"indices": []
		},
		{
			"loop": false,
			"offsets": [
				-80,
				11
			],
			"anim": "singRIGHT",
			"fps": 24,
			"name": "Ace Left Note",
			"indices": []
		},
		{
			"loop": false,
			"offsets": [
				54,
				40
			],
			"anim": "singUP",
			"fps": 24,
			"name": "Ace Up Note",
			"indices": []
		},
		{
			"loop": false,
			"offsets": [
				157,
				19
			],
			"anim": "singLEFT",
			"fps": 24,
			"name": "Ace Right Note",
			"indices": []
		}
	],
	"no_antialiasing": false,
	"image": "characters/atrocity/ace",
	"position": [
		0,
		-120
	],
	"healthicon": "atrocity/icon-ace",
	"flip_x": false,
	"healthbar_colors": [
		186,
		226,
		255
	],
	"playable": true,
	"camera_position": [
		0,
		0
	],
	"sing_duration": 6.1,
	"scale": 1
}