{
	"animations": [
		{
			"loop": true,
			"offsets": [
				0,
				0
			],
			"anim": "idle",
			"fps": 24,
			"name": "Idle",
			"indices": []
		},
		{
			"loop": false,
			"offsets": [
				-36,
				68
			],
			"anim": "Hank",
			"fps": 24,
			"name": "Hank",
			"indices": []
		},
		{
			"loop": false,
			"offsets": [
				-36,
				68
			],
			"anim": "hurt",
			"fps": 24,
			"name": "Hank",
			"indices": []
		},
		{
			"loop": false,
			"offsets": [
				190,
				50
			],
			"anim": "singLEFT",
			"fps": 24,
			"name": "Sing Left",
			"indices": []
		},
		{
			"loop": false,
			"offsets": [
				-260,
				-40
			],
			"anim": "singRIGHT",
			"fps": 24,
			"name": "Sing Right",
			"indices": []
		},
		{
			"loop": false,
			"offsets": [
				-100,
				-230
			],
			"anim": "singDOWN",
			"fps": 24,
			"name": "Sing Down",
			"indices": []
		},
		{
			"loop": false,
			"offsets": [
				-10,
				140
			],
			"anim": "singUP",
			"fps": 24,
			"name": "Sing Up",
			"indices": []
		}
	],
	"no_antialiasing": false,
	"image": "characters/expurgation/EXTRICKY",
	"position": [
		0,
		140
	],
	"healthicon": "expurgation/extiky",
	"flip_x": false,
	"healthbar_colors": [
		255,
		25,
		0
	],
	"camera_position": [
		-100,
		-100
	],
	"sing_duration": 6.1,
	"scale": 2
}