{
	"animations": [
		{
			"offsets": [
				0,
				0
			],
			"loop": false,
			"fps": 24,
			"anim": "idle",
			"indices": [],
			"name": "idle"
		},
		{
			"offsets": [
				0,
				0
			],
			"loop": false,
			"fps": 24,
			"anim": "singLEFT",
			"indices": [
				0,
				1,
				2,
				3,
				4,
				5,
				6,
				7,
				8,
				9,
				10,
				11,
				12,
				13,
				14
			],
			"name": "left"
		},
		{
			"offsets": [
				0,
				0
			],
			"loop": false,
			"fps": 24,
			"anim": "singRIGHT",
			"indices": [
				0,
				1,
				2,
				3,
				4,
				5,
				6,
				7,
				8,
				9,
				10,
				11,
				12,
				13,
				14
			],
			"name": "right"
		},
		{
			"offsets": [
				0,
				0
			],
			"loop": false,
			"fps": 24,
			"anim": "singDOWN",
			"indices": [
				0,
				1,
				2,
				3,
				4,
				5,
				6,
				7,
				8,
				9,
				10,
				11,
				12,
				13,
				14
			],
			"name": "down"
		},
		{
			"offsets": [
				0,
				0
			],
			"loop": false,
			"fps": 24,
			"anim": "singUP",
			"indices": [
				0,
				1,
				2,
				3,
				4,
				5,
				6,
				7,
				8,
				9,
				10,
				11,
				12,
				13,
				14
			],
			"name": "up"
		}
	],
	"no_antialiasing": true,
	"image": "characters/atrocity/luigi",
	"position": [
		170,
		540
	],
	"healthicon": "atrocity/luigi",
	"flip_x": true,
	"healthbar_colors": [
		0,
		148,
		0
	],
	"playable": false,
	"camera_position": [
		-350,
		-100
	],
	"sing_duration": 4,
	"scale": 20
}