{
	"animations": [
		{
			"loop": false,
			"offsets": [
				0,
				0
			],
			"anim": "idle",
			"fps": 24,
			"name": "sky mad idle",
			"indices": []
		},
		{
			"loop": false,
			"offsets": [
				0,
				0
			],
			"anim": "singLEFT",
			"fps": 24,
			"name": "sky mad left",
			"indices": []
		},
		{
			"loop": false,
			"offsets": [
				0,
				0
			],
			"anim": "singDOWN",
			"fps": 24,
			"name": "sky mad down",
			"indices": []
		},
		{
			"loop": false,
			"offsets": [
				20,
				-7
			],
			"anim": "singUP",
			"fps": 24,
			"name": "sky mad up",
			"indices": []
		},
		{
			"loop": false,
			"offsets": [
				0,
				0
			],
			"anim": "singRIGHT",
			"fps": 24,
			"name": "sky mad right",
			"indices": []
		}
	],
	"no_antialiasing": false,
	"image": "characters/headache/sky_mad_assets",
	"position": [
		0,
		160
	],
	"healthicon": "headache/sky-mad",
	"flip_x": false,
	"healthbar_colors": [
		255,
		0,
		0
	],
	"playable": false,
	"camera_position": [
		0,
		50
	],
	"sing_duration": 6.1,
	"scale": 1
}